FFEM/FFEM.py
FFEM/__init__.py
FFEM-0.4.4.data/scripts/FFEM.py
FFEM-0.4.4.dist-info/LICENSE
FFEM-0.4.4.dist-info/METADATA
FFEM-0.4.4.dist-info/WHEEL
FFEM-0.4.4.dist-info/top_level.txt
FFEM-0.4.4.dist-info/RECORD
