Metadata-Version: 2.1
Name: FFEM
Version: 0.4.4
Summary: Easy and Fast Facial Emotion Monitoring
Home-page: https://github.com/WiseGeorge/Fast-Facial-Emotion-Monitoring-FFEM-Package
Author: Jorge Felix Martinez
Author-email: jorgito16040@gmail.com
License: MIT
Classifier: Programming Language :: Python :: 3
Classifier: License :: OSI Approved :: MIT License
Classifier: Operating System :: OS Independent
License-File: LICENSE
Requires-Dist: deepface ==0.0.79
Requires-Dist: tensorflow ==2.10
Requires-Dist: keras ==2.10.0
Requires-Dist: mediapipe ==0.10.0
Requires-Dist: opencv-contrib-python ==4.8.1.78
Requires-Dist: opencv-python ==4.6.0.66
